synthesisai/__init__.py
synthesisai/data_types.py
synthesisai/dataset.py
synthesisai/item_loader.py
synthesisai/item_loader_factory.py
synthesisai/item_loader_v1.py
synthesisai/item_loader_v2.py
synthesisai/modality.py
synthesisai-0.5.2.dist-info/LICENSE
synthesisai-0.5.2.dist-info/METADATA
synthesisai-0.5.2.dist-info/WHEEL
synthesisai-0.5.2.dist-info/top_level.txt
synthesisai-0.5.2.dist-info/RECORD
