Metadata-Version: 2.1
Name: synthesisai
Version: 0.5.2
Summary: Python library for loading synthetic data for ML use cases
Home-page: https://github.com/Synthesis-AI-Dev/synthesisai
Author: Synthesis AI
Author-email: anish@synthesis.ai
License: MIT license
Keywords: synthesisai
Classifier: Development Status :: 2 - Pre-Alpha
Classifier: Intended Audience :: Developers
Classifier: License :: OSI Approved :: MIT License
Classifier: Natural Language :: English
Classifier: Programming Language :: Python :: 3
Classifier: Programming Language :: Python :: 3.6
Classifier: Programming Language :: Python :: 3.7
Classifier: Programming Language :: Python :: 3.8
Requires-Python: >=3.6
License-File: LICENSE
Requires-Dist: tiffile (>=2018.10.18)
Requires-Dist: opencv-python (>=4.5.1.48)
Requires-Dist: imagecodecs (>=2021.1.28)
Requires-Dist: numpy (>=1.20.1)
Requires-Dist: pandas (>=1.3.5)
Requires-Dist: pytest (>=6.2.5)
Requires-Dist: jupyter (>=1.0.0)
Requires-Dist: matplotlib (>=3.2.2)
Requires-Dist: albumentations (>=1.1.0)
Requires-Dist: plotly (>=5.5.0)
Requires-Dist: sphinx-rtd-theme (>=1.0.0)
